qikits/__init__.py
qikits/sampling/__init__.py
qikits/sampling/weighted_sampling.py
qikits-0.1.1.dist-info/licenses/LICENSE
qikits-0.1.1.dist-info/METADATA
qikits-0.1.1.dist-info/WHEEL
qikits-0.1.1.dist-info/top_level.txt
qikits-0.1.1.dist-info/RECORD
