Metadata-Version: 2.4
Name: qikits
Version: 0.1.1
Summary: A toolkit of curated algorithms, data structures, and reusable code snippets.
Author-email: Qikai Gu <qikai.gu88@gmail.com>
License-Expression: MIT
Project-URL: Homepage, https://github.com/qikaigu/qikits
Project-URL: Issues, https://github.com/qikaigu/qikits/issues
Classifier: Programming Language :: Python :: 3
Classifier: Operating System :: OS Independent
Requires-Python: <4,>=3.10.1
License-File: LICENSE
Requires-Dist: pyspark>=3.0.0
Dynamic: license-file
